odoo/addons/product_attribute_set/README.rst
odoo/addons/product_attribute_set/__init__.py
odoo/addons/product_attribute_set/__manifest__.py
odoo/addons/product_attribute_set/demo/product_attribute.xml
odoo/addons/product_attribute_set/i18n/es.po
odoo/addons/product_attribute_set/i18n/es_AR.po
odoo/addons/product_attribute_set/i18n/fr.po
odoo/addons/product_attribute_set/i18n/fr_BE.po
odoo/addons/product_attribute_set/i18n/it.po
odoo/addons/product_attribute_set/i18n/product_attribute_set.pot
odoo/addons/product_attribute_set/i18n/tr.po
odoo/addons/product_attribute_set/models/__init__.py
odoo/addons/product_attribute_set/models/attribute_attribute.py
odoo/addons/product_attribute_set/models/product.py
odoo/addons/product_attribute_set/models/product_category.py
odoo/addons/product_attribute_set/readme/CONTRIBUTORS.md
odoo/addons/product_attribute_set/readme/DESCRIPTION.md
odoo/addons/product_attribute_set/readme/ROADMAP.md
odoo/addons/product_attribute_set/readme/USAGE.md
odoo/addons/product_attribute_set/static/description/icon.png
odoo/addons/product_attribute_set/static/description/index.html
odoo/addons/product_attribute_set/views/product.xml
odoo/addons/product_attribute_set/views/product_category.xml
odoo_addon_product_attribute_set-18.0.1.0.0.2.dist-info/METADATA
odoo_addon_product_attribute_set-18.0.1.0.0.2.dist-info/WHEEL
odoo_addon_product_attribute_set-18.0.1.0.0.2.dist-info/top_level.txt
odoo_addon_product_attribute_set-18.0.1.0.0.2.dist-info/RECORD
