Metadata-Version: 2.1
Name: odoo-addon-product_attribute_set
Version: 18.0.1.0.0.2
Requires-Python: >=3.10
Requires-Dist: odoo-addon-attribute_set==18.0.*
Requires-Dist: odoo==18.0.*
Summary: Product Attribute Set
Home-page: https://github.com/OCA/odoo-pim
License: AGPL-3
Author: Akretion,Odoo Community Association (OCA)
Author-email: support@odoo-community.org
Classifier: Programming Language :: Python
Classifier: Framework :: Odoo
Classifier: Framework :: Odoo :: 18.0
Classifier: License :: OSI Approved :: GNU Affero General Public License v3
